jfrog/__init__.py
jfrog/artifactory.py
jfrog/migration.py
jfrog/missioncontrol.py
jfrog/platform.py
jfrog/support.py
jfrog/utilities.py
jfrog/xray.py
jfrog_client-1.2.3.dist-info/LICENSE
jfrog_client-1.2.3.dist-info/METADATA
jfrog_client-1.2.3.dist-info/WHEEL
jfrog_client-1.2.3.dist-info/top_level.txt
jfrog_client-1.2.3.dist-info/RECORD
