Metadata-Version: 2.1
Name: jfrog-client
Version: 1.2.3
Summary: Package that creates simple APIs to interact with Jfrog
Home-page: https://github.com/peterdeames/jfrog-client
Keywords: jfrog
Classifier: Development Status :: 4 - Beta
Classifier: Intended Audience :: Developers
Classifier: Intended Audience :: System Administrators
Classifier: Programming Language :: Python :: 3 :: Only
Classifier: Topic :: Utilities
Classifier: Operating System :: OS Independent
License-File: LICENSE
Requires-Dist: requests
Requires-Dist: tabulate
Requires-Dist: logging
Requires-Dist: packaging
Requires-Dist: tqdm
